arcus/__init__.py
arcus/api.py
arcus/http_helper.py
arcus/rabbitmq.py
arcus_sdk-0.1.6.dist-info/METADATA
arcus_sdk-0.1.6.dist-info/WHEEL
arcus_sdk-0.1.6.dist-info/top_level.txt
arcus_sdk-0.1.6.dist-info/RECORD
