Metadata-Version: 2.1
Name: arcus-sdk
Version: 0.1.6
Summary: arcus sdk
Home-page: https://helix.yitu-inc.com
Author: tuo.zhou
Author-email: tuo.zhou@yitu-inc.com
License: MIT Licence
Keywords: performance test,arcus
Platform: any
Requires-Python: >=3
Requires-Dist: pika
Requires-Dist: requests
